{
  "setting": {},
  "condition": {
    "plugin": {
      "list": []
    },
    "game": {
      "list": []
    },
    "gamePlugin": {
      "list": []
    },
    "miniprogram": {
      "list": [
        {
          "name": "pages/list/index",
          "pathName": "pages/list/index",
          "query": "",
          "scene": null
        },
        {
          "name": "创建订单",
          "pathName": "subpages/cart/create/index",
          "query": "",
          "scene": null
        }
      ]
    }
  }
}